nba_stats/__init__.py
nba_stats/constant.py
nba_stats/fantasy_nba.py
nba_stats/nba_stats.py
py_nba_stats-0.0.4.dist-info/LICENSE
py_nba_stats-0.0.4.dist-info/METADATA
py_nba_stats-0.0.4.dist-info/WHEEL
py_nba_stats-0.0.4.dist-info/top_level.txt
py_nba_stats-0.0.4.dist-info/RECORD
