Metadata-Version: 2.1
Name: py-nba-stats
Version: 0.0.4
Summary: A package for scraping NBA stats from yahoo
Home-page: https://github.com/monootc/nba_stats
Author: Kelvin Hu
Author-email: kelvin.hu.1203@gmail.com
License: UNKNOWN
Platform: UNKNOWN
Classifier: Programming Language :: Python :: 3
Classifier: License :: OSI Approved :: MIT License
Classifier: Operating System :: OS Independent
Requires-Python: >=3.6
